[
  {
    "outputFileName": "wwwroot/css/site.min.css",
    "inputFiles": [
      "wwwroot/css/site.css",
      "wwwroot/css/wait.css"
    ],
    "minify": {
      "enabled": true
    }
  },
  {
    "outputFileName": "wwwroot/js/site.min.js",
    "inputFiles": [
      "wwwroot/js/site.js",
      "wwwroot/js/swipRefresh.js"
    ],
    "minify": {
      "enabled": true,
      "renameLocals": true
    },
    "sourceMap": false
  },
  {
    "outputFileName": "wwwroot/js/game.min.js",
    "inputFiles": [
      "wwwroot/js/game.js",
      "wwwroot/js/swipRefresh.js",
      "wwwroot/js/domManipulation.js",
      "wwwroot/js/ajaxCall.js",
      "wwwroot/js/ajaxCallback.js"
    ],
    "minify": {
      "enabled": true,
      "renameLocals": true
    },
    "sourceMap": false
  }
]